fastapi_auth_service/__init__.py
fastapi_auth_service/__main__.py
fastapi_auth_service/authentication.py
fastapi_auth_service/conf.py
fastapi_auth_service/core.py
fastapi_auth_service/helpers.py
fastapi_auth_service/jobs.py
fastapi_auth_service/api/__init__.py
fastapi_auth_service/api/http.py
fastapi_auth_service/api/users.py
fastapi_auth_service/api/v1/__init__.py
fastapi_auth_service/api/v1/endpoints.py
fastapi_auth_service/api/v1/schemas.py
fastapi_auth_service/db/__init__.py
fastapi_auth_service/db/alembic.ini
fastapi_auth_service/db/helpers.py
fastapi_auth_service/db/models.py
fastapi_auth_service/db/redis.py
fastapi_auth_service/db/user_db_helpers.py
fastapi_auth_service/db/migrations/__init__.py
fastapi_auth_service/db/migrations/env.py
fastapi_auth_service/db/migrations/script.py.mako
fastapi_auth_service/db/migrations/versions/20221228143345_de8dea98760e_initial.py
fastapi_auth_service/logging/__init__.py
fastapi_auth_service/logging/filters.py
fastapi_auth_service/logging/formatter.py
fastapi_auth_service-0.0.7.dist-info/AUTHORS.rst
fastapi_auth_service-0.0.7.dist-info/LICENSE
fastapi_auth_service-0.0.7.dist-info/METADATA
fastapi_auth_service-0.0.7.dist-info/WHEEL
fastapi_auth_service-0.0.7.dist-info/top_level.txt
fastapi_auth_service-0.0.7.dist-info/RECORD
