Metadata-Version: 2.1
Name: fastapi-auth-service
Version: 0.0.7
Summary: FastAPI auth service
Home-page: https://github.com/kamikaze/fastapi-auth-service
Author: Oleg Korsak
Author-email: kamikaze.is.waiting.you@gmail.com
License: gpl-3
Project-URL: Documentation, https://github.com/kamikaze/fastapi-auth-service
Platform: any
Classifier: Development Status :: 4 - Beta
Classifier: Programming Language :: Python
Requires-Python: >=3.11
License-File: LICENSE
License-File: AUTHORS.rst
Requires-Dist: alembic (==1.9.1)
Requires-Dist: asyncpg (==0.27.0)
Requires-Dist: Authlib (==1.2.0)
Requires-Dist: fastapi (==0.89.1)
Requires-Dist: fastapi-pagination (==0.11.2)
Requires-Dist: fastapi-users[redis,sqlalchemy] (==10.2.1)
Requires-Dist: orjson (==3.8.5)
Requires-Dist: passlib[argon2] (==1.7.4)
Requires-Dist: pydantic (==1.10.4)
Requires-Dist: PyJWT (==2.6.0)
Requires-Dist: python-dateutil (==2.8.2)
Requires-Dist: redis (==4.4.1)
Requires-Dist: SQLAlchemy (==1.4.46)
Requires-Dist: uvicorn[standard] (==0.20.0)
Requires-Dist: uvloop (==0.17.0)
Provides-Extra: testing
Requires-Dist: pytest ; extra == 'testing'
Requires-Dist: pytest-cov ; extra == 'testing'
